gemflix/analysis/__init__.py
gemflix/analysis/data_preprocessing.py
gemflix/analysis/visualization.py
gemflix/collection/__init__.py
gemflix/collection/collection.py
gemflix/collection/collection_interface.py
gemflix/search/__init__.py
gemflix/search/filter.py
gemflix/search/hybrid_search.py
gemflix/utils/__init__.py
gemflix/utils/database.py
gemflix/utils/exceptions.py
gemflix/utils/generative_ai.py
gemflix-0.0.1.dist-info/METADATA
gemflix-0.0.1.dist-info/WHEEL
gemflix-0.0.1.dist-info/top_level.txt
gemflix-0.0.1.dist-info/RECORD
