Metadata-Version: 2.1
Name: gemflix
Version: 0.0.1
Summary: A Python-powered movie collection management system
Author-email: jenny-chung301 <je.chung301@gmail.com>, j232shen <janexshen@gmail.com>
Project-URL: homepage, https://github.com/j232shen/movie-collection
Project-URL: issues, https://github.com/j232shen/movie-collection/issues
Classifier: Programming Language :: Python :: 3
Classifier: License :: OSI Approved :: MIT License
Classifier: Operating System :: OS Independent
Requires-Python: >=3.11
Requires-Dist: pandas>=2.2.2
Requires-Dist: matplotlib>=3.8.4
Requires-Dist: numpy>=2.1.3
Requires-Dist: google-generativeai>=0.8.3
Requires-Dist: python-dotenv>=1.0.1
Requires-Dist: langchain-couchbase>=0.2.2
Requires-Dist: tqdm>=4.67.0
Requires-Dist: pygal>=3.0.5
